numba_scipy_complex/__init__.py
numba_scipy_complex/src/__init__.py
numba_scipy_complex/src/functions/__init__.py
numba_scipy_complex/src/functions/gamma.py
numba_scipy_complex/tests/__init__.py
numba_scipy_complex/tests/test_utils.py
numba_scipy_complex/tests/functions/__init__.py
numba_scipy_complex/tests/functions/gamma.py
numba_scipy_complex-0.1.0.dist-info/LICENSE
numba_scipy_complex-0.1.0.dist-info/METADATA
numba_scipy_complex-0.1.0.dist-info/WHEEL
numba_scipy_complex-0.1.0.dist-info/top_level.txt
numba_scipy_complex-0.1.0.dist-info/RECORD
